pytest_web3_data/__about__.py
pytest_web3_data/__init__.py
pytest_web3_data-0.2.1.dist-info/METADATA
pytest_web3_data-0.2.1.dist-info/WHEEL
pytest_web3_data-0.2.1.dist-info/entry_points.txt
pytest_web3_data-0.2.1.dist-info/licenses/LICENSE.txt
pytest_web3_data-0.2.1.dist-info/RECORD
