Metadata-Version: 2.1
Name: pytest-web3-data
Version: 0.2.1
Summary: A pytest plugin to fetch test data from IPFS HTTP gateways during pytest execution.
Project-URL: Documentation, https://github.com/thewtex/pytest-web3-data#readme
Project-URL: Issues, https://github.com/thewtex/pytest-web3-data/issues
Project-URL: Source, https://github.com/thewtex/pytest-web3-data
Author-email: Matt McCormick <matt@mmmccormick.com>
License-Expression: MIT
License-File: LICENSE.txt
Keywords: data,ipfs,pytest,web3
Classifier: Development Status :: 4 - Beta
Classifier: Framework :: Pytest
Classifier: Programming Language :: Python
Classifier: Programming Language :: Python :: 3.7
Classifier: Programming Language :: Python :: 3.8
Classifier: Programming Language :: Python :: 3.9
Classifier: Programming Language :: Python :: 3.10
Classifier: Programming Language :: Python :: 3.11
Classifier: Programming Language :: Python :: 3.12
Classifier: Programming Language :: Python :: Implementation :: CPython
Classifier: Programming Language :: Python :: Implementation :: PyPy
Requires-Python: >=3.7
Requires-Dist: py-cid
Requires-Dist: pytest
Requires-Dist: urllib3
